{"country": "Vietnam", "city": "Hanoi", "longitude": "105.794059", "latitude": "21.009984", "name": "Dream Gold Hotel 2 Hanoi", "stars": "3", "address": "No.37, Alley No.20, Nguyen Chanh Street, Trung Hoa Nhan Chinh, Hanoi, Vietnam", "url": "https://www.agoda.com/dream-gold-hotel-2-hanoi/hotel/hanoi-vn.html", "hotelId": 1636244, "hotelDesc": "Renovated in 2017, the Dream Gold Hotel 2 Hanoi guarantees guests a pleasant stay whether in Hanoi for business or pleasure. From here, guests can enjoy easy access to all that the lively city has to offer. With its convenient location, the hotel offers easy access to the city's must-see destinations.<BR><BR> Take advantage of a wealth of unrivaled services and amenities at this Hanoi hotel. This hotel offers numerous on-site facilities to satisfy even the most discerning guest.<BR><BR> All guest accommodations feature thoughtful amenities to ensure an unparalleled sense of comfort. The hotel's recreational facilities, which include mini golf course, hot tub, fitness center, sauna, spa are designed for escape and relaxation. Whatever your purpose of visit, Dream Gold Hotel 2 Hanoi is an excellent choice for your stay in Hanoi.", "usefulInfo": [{"Name": "Check-in/Check-out", "Items": [{"Title": "Reception open until", "Description": "12:00 pm"}]}, {"Name": "Getting around", "Items": [{"Title": "Distance from city center", "Description": "6km"}, {"Title": "Travel time to airport (minutes)", "Description": "30"}]}, {"Name": "The property", "Items": [{"Title": "Non-smoking rooms/floors", "Description": "no"}, {"Title": "Number of bars/lounges\n", "Description": "0"}, {"Title": "Number of floors", "Description": "8"}, {"Title": "Number of restaurants", "Description": "1"}, {"Title": "Number of rooms ", "Description": "44"}, {"Title": "Year hotel opened", "Description": "2015"}, {"Title": "Most recent hotel renovation\n", "Description": "2017"}]}], "features": [{"Internet access": ["Free Wi-Fi in all rooms"]}, {"Things to do, ways to relax": ["Fitness center", "Hot tub", "Massage", "Mini golf course", "Sauna", "Spa", "Steamroom"]}, {"Services and conveniences": ["Smoking area"]}, {"Access": ["Pets allowed"]}, {"Available in all rooms": ["Desk", "Free bottled water", "Mini bar", "Mirror", "Smoking allowed", "Telephone", "Toiletries"]}, {"Languages spoken": ["English", "Korean", "Vietnamese"]}], "rooms": [{"id": 12314692, "name": "Twin Room with Bath", "facilities": {"Bathroom and toiletries": ["Bathrobes", "Hair dryer", "Mirror", "Toiletries", "Towels"], "Entertainment ": ["Telephone", "TV"], "Comforts": ["Air conditioning", "Heating"], "Dining, drinking, and snacking": ["Mini bar"], "Layout and furnishings": ["Desk", "Seating area"], "Safety and security features": ["In-room safe box"]}}, {"id": 11042291, "name": "Superior", "facilities": {"Bathroom and toiletries": ["Bathrobes", "Hair dryer", "Mirror", "Toiletries", "Towels"], "Entertainment ": ["Telephone", "TV [flat screen]", "Wi-Fi [free]"], "Comforts": ["Air conditioning", "Blackout curtains", "Daily newspaper", "Heating", "Linens", "Slippers", "Umbrella"], "Dining, drinking, and snacking": ["Free bottled water", "Free instant coffee", "Mini bar", "Refrigerator"], "Layout and furnishings": ["Desk", "Laptop workspace", "Seating area", "Separate dining area", "Wooden/parqueted flooring"], "Clothing and laundry": ["Closet", "Ironing facilities"], "Safety and security features": ["Fire extinguisher", "First aid kit", "In-room safe box"]}}, {"id": 11042314, "name": "Deluxe", "facilities": {"Bathroom and toiletries": ["Bathrobes", "Cleaning products", "Hair dryer", "Mirror", "Toiletries", "Towels"], "Entertainment ": ["Telephone", "TV [flat screen]", "Wi-Fi [free]"], "Comforts": ["Air conditioning", "Blackout curtains", "Daily newspaper", "Fan", "Heating", "Linens", "Slippers", "Soundproofing", "Umbrella", "Wake-up service"], "Dining, drinking, and snacking": ["Free instant coffee", "Free welcome drink", "Mini bar", "Refrigerator"], "Layout and furnishings": ["Desk", "Laptop workspace", "Seating area", "Separate dining area", "Wooden/parqueted flooring"], "Clothing and laundry": ["Closet", "Ironing facilities", "Washing machine"], "Safety and security features": ["Fire extinguisher", "First aid kit", "In-room safe box", "Locker"]}}, {"id": 11042155, "name": "Standard", "facilities": {"Bathroom and toiletries": ["Bathrobes", "Hair dryer", "Mirror", "Toiletries", "Towels"], "Entertainment ": ["Telephone", "TV [flat screen]", "Wi-Fi [free]"], "Comforts": ["Air conditioning", "Blackout curtains", "Daily newspaper", "Fan", "Heating", "Linens", "Slippers", "Soundproofing", "Umbrella"], "Dining, drinking, and snacking": ["Complimentary tea", "Free bottled water", "Free instant coffee", "Mini bar", "Refrigerator"], "Layout and furnishings": ["Desk", "Laptop workspace", "Seating area", "Separate dining area", "Wooden/parqueted flooring"], "Clothing and laundry": ["Closet", "Clothes dryer", "Ironing facilities"], "Safety and security features": ["In-room safe box"]}}, {"id": 11042333, "name": "Deluxe Twin", "facilities": {"Bathroom and toiletries": ["Cleaning products", "Hair dryer", "Mirror", "Toiletries", "Towels"], "Entertainment ": ["Telephone", "TV [flat screen]", "Wi-Fi [free]"], "Comforts": ["Air conditioning", "Alarm clock", "Blackout curtains", "Daily newspaper", "Fan", "Linens", "Slippers", "Soundproofing", "Umbrella"], "Dining, drinking, and snacking": ["Complimentary tea", "Free instant coffee", "Free welcome drink", "Mini bar", "Refrigerator"], "Layout and furnishings": ["Desk", "Laptop workspace", "Separate dining area", "Wooden/parqueted flooring"], "Clothing and laundry": ["Closet", "Clothes dryer", "Ironing facilities", "Washing machine"], "Safety and security features": ["Fire extinguisher", "First aid kit", "Laptop safe box", "Locker"]}}, {"id": 12451822, "name": "Junior", "facilities": {"Bathroom and toiletries": ["Mirror", "Toiletries", "Towels"], "Entertainment ": ["Satellite/cable channels", "Telephone"], "Dining, drinking, and snacking": ["Mini bar"], "Layout and furnishings": ["Desk", "Seating area"]}}], "nearbyProperties": [{"categoryName": "Airports", "places": [{"distance": 10.2, "distanceDisplay": "10 kilometers to", "distanceUnit": "kilometers to", "name": "Gia Lam Airport (VGL)"}, {"distance": 23.05, "distanceDisplay": "23 kilometers to", "distanceUnit": "kilometers to", "name": "Noi Bai International Airport (HAN)"}]}, {"categoryName": "Public transportation", "places": [{"distance": 5.25, "distanceDisplay": "5 kilometers to", "distanceUnit": "kilometers to", "name": "Hanoi Railway Station"}, {"distance": 5.36, "distanceDisplay": "5 kilometers to", "distanceUnit": "kilometers to", "name": "Le Duan Railway Station"}]}, {"categoryName": "Hospital or clinic", "places": [{"distance": 1.62, "distanceDisplay": "1.6 kilometers to", "distanceUnit": "kilometers to", "name": "Benh Vien Y Hoc Co Truyen Bo Cong An"}]}, {"categoryName": "Pharmacy", "places": [{"distance": 1.15, "distanceDisplay": "1.1 kilometers to", "distanceUnit": "kilometers to", "name": "Hien Vi Drugstore"}]}, {"categoryName": "Convenience store", "places": [{"distance": 0.87, "distanceDisplay": "850 meters to", "distanceUnit": "kilometers to", "name": "Vinmart"}]}, {"categoryName": "Cash withdrawal", "places": [{"distance": 1.23, "distanceDisplay": "1.2 kilometers to", "distanceUnit": "kilometers to", "name": "ATM"}]}]}