{"country": "Vietnam", "city": "Hanoi", "longitude": "105.847885608673", "latitude": "21.0288710668284", "name": "Hanoi New Hotel - Phu Doan", "stars": "2", "address": "41 Phu Doan street, Hoan Kiem District, Hanoi, Vietnam, 10000", "url": "https://www.agoda.com/hanoi-new-hotel-phu-doan/hotel/hanoi-vn.html", "hotelId": 535522, "hotelDesc": "Whether you're a tourist or traveling on business, Hanoi New Hotel - Phu Doan is a great choice for accommodation when visiting Hanoi. Situated only 0.3 km from the city center, guests are well located to enjoy the town's attractions and activities. For sightseeing options and local attractions, one need not look far as the hotel enjoys close proximity to Magonn Design, Vietnam Country Tour - Day Tours, Nha Tho.<BR><BR> At Hanoi New Hotel - Phu Doan, every effort is made to make guests feel comfortable. To do so, the hotel provides the best in services and amenities. Free Wi-Fi in all rooms, Wi-Fi in public areas, room service, airport transfer, family room are just a few of the facilities that set Hanoi New Hotel - Phu Doan apart from other hotels in the city. <BR><BR> Step into one of 15 inviting rooms and escape the stresses of the day with a wide range of amenities such as television LCD/plasma screen, internet access \u2013 wireless, internet access \u2013 wireless (complimentary), non smoking rooms, air conditioning which can be found in some rooms. Besides, the hotel's host of recreational offerings ensures you have plenty to do during your stay. Superb facilities and an excellent location make the Hanoi New Hotel - Phu Doan the perfect base from which to enjoy your stay in Hanoi.", "usefulInfo": [{"Name": "Check-in/Check-out", "Items": [{"Title": "Check-in from", "Description": "01:00 PM"}, {"Title": "Check-out until", "Description": "12:00 PM"}, {"Title": "Reception open until", "Description": "12:00 PM"}]}, {"Name": "Getting around", "Items": [{"Title": "Airport transfer fee", "Description": "380000 VND"}, {"Title": "Distance from city center", "Description": "0.3 km"}, {"Title": "Travel time to airport (minutes)", "Description": "45"}]}, {"Name": "The property", "Items": [{"Title": "Number of floors", "Description": "5"}, {"Title": "Number of restaurants", "Description": "1"}, {"Title": "Number of rooms ", "Description": "15"}, {"Title": "Year hotel opened", "Description": "2012"}, {"Title": "Most recent hotel renovation", "Description": "2013"}]}], "features": [{"Internet access": ["Free Wi-Fi in all rooms", "Wi-Fi in public areas"]}, {"Getting around": ["Airport transfer", "Bicycle rental"]}, {"Things to do, ways to relax": ["Tours"]}, {"Dining, drinking, and snacking": ["Room service"]}, {"Services and conveniences": ["Laundry service", "Safety deposit boxes", "Smoking area"]}, {"For the kids": ["Family room"]}, {"Access": ["Elevator", "Pets allowed"]}, {"Available in all rooms": ["Air conditioning", "Desk", "Free bottled water", "Internet access \u2013 wireless", "Mini bar", "Satellite/cable channels", "Shower", "TV"]}, {"Languages spoken": ["Vietnamese"]}], "rooms": [{"id": 4010006, "name": "Superior", "facilities": {"Bathroom and toiletries": ["Bathrobes", "Hair dryer", "Mirror", "Toiletries", "Towels"], "Entertainment ": ["Free Wi-Fi in all rooms", "Satellite/cable channels", "Telephone"], "Comforts": ["Air conditioning"], "Dining, drinking, and snacking": ["Coffee/tea maker", "Mini bar"], "Layout and furnishings": ["Desk", "Seating area"]}}, {"id": 5649345, "name": "Triple Room", "facilities": {"Bathroom and toiletries": ["Hair dryer", "Toiletries"], "Entertainment ": ["Free Wi-Fi in all rooms", "Satellite/cable channels", "Telephone"], "Comforts": ["Air conditioning"], "Dining, drinking, and snacking": ["Mini bar"], "Layout and furnishings": ["Desk", "Seating area"]}}, {"id": 4425972, "name": "Superior Triple", "facilities": {"Entertainment ": ["Free Wi-Fi in all rooms", "Satellite/cable channels", "Telephone"], "Comforts": ["Air conditioning"], "Dining, drinking, and snacking": ["Mini bar"], "Layout and furnishings": ["Desk", "Seating area"]}}, {"id": 5652783, "name": "Triple Room with Private Bathroom", "facilities": {"Bathroom and toiletries": ["Hair dryer", "Toiletries"], "Entertainment ": ["Free Wi-Fi in all rooms", "Satellite/cable channels", "Telephone"], "Comforts": ["Air conditioning"], "Dining, drinking, and snacking": ["Mini bar"], "Layout and furnishings": ["Desk", "Seating area"]}}, {"id": 4010008, "name": "Deluxe Family", "facilities": {"Bathroom and toiletries": ["Bathrobes", "Hair dryer", "Mirror", "Toiletries", "Towels"], "Entertainment ": ["Free Wi-Fi in all rooms", "Satellite/cable channels", "Telephone"], "Comforts": ["Air conditioning"], "Dining, drinking, and snacking": ["Coffee/tea maker", "Mini bar"], "Layout and furnishings": ["Desk", "Seating area"], "Clothing and laundry": ["Closet", "Ironing facilities"]}}, {"id": 4010007, "name": "Deluxe", "facilities": {"Bathroom and toiletries": ["Hair dryer", "Toiletries"], "Entertainment ": ["Free Wi-Fi in all rooms", "Satellite/cable channels", "Telephone"], "Comforts": ["Air conditioning"], "Dining, drinking, and snacking": ["Coffee/tea maker", "Mini bar"], "Layout and furnishings": ["Desk", "Seating area"]}}], "nearbyProperties": [{"categoryName": "Airports", "places": [{"distance": 4.23, "distanceDisplay": "4.2 km", "distanceUnit": "km", "name": "Gia Lam Airport (VGL)"}, {"distance": 21.39, "distanceDisplay": "21 km", "distanceUnit": "km", "name": "Noi Bai International Airport (HAN)"}]}, {"categoryName": "Public transportation", "places": [{"distance": 0.65, "distanceDisplay": "600 m", "distanceUnit": "km", "name": "Le Duan Railway Station"}, {"distance": 0.81, "distanceDisplay": "800 m", "distanceUnit": "km", "name": "Hanoi Railway Station"}]}, {"categoryName": "Hospital or clinic", "places": [{"distance": 0.26, "distanceDisplay": "250 m", "distanceUnit": "km", "name": "Benh Vien Phu San Ha Noi"}]}, {"categoryName": "Pharmacy", "places": [{"distance": 0.31, "distanceDisplay": "300 m", "distanceUnit": "km", "name": "Dong Y Gia Truyen Drugstore"}]}, {"categoryName": "Convenience store", "places": [{"distance": 0.59, "distanceDisplay": "550 m", "distanceUnit": "km", "name": "Circle K"}]}, {"categoryName": "Cash withdrawal", "places": [{"distance": 0.54, "distanceDisplay": "500 m", "distanceUnit": "km", "name": "ATM"}]}]}