{"country": "Vietnam", "city": "Hanoi", "longitude": "105.776886", "latitude": "21.010582", "name": "ISTAY Hotel Apartment 5", "stars": "", "address": "45/4 Dong Me, Me Tri, Nam Tu Liem, My Dinh National Stadium, Hanoi, Vietnam", "url": "https://www.agoda.com/istay-hotel-apartment-5/hotel/hanoi-vn.html", "hotelId": 2241020, "hotelDesc": "Featuring free WiFi and air conditioning, ISTAY Hotel Apartment 5 is located in Hanoi, 1.6 km from My Dinh Stadium. Vincom Center Nguyen Chi Thanh is 3.6 km from the property. Free private parking is available on site.\n\nThe accommodation features a satellite flat-screen TV. There is also a kitchen, equipped with a microwave. A fridge and stovetop are also offered, as well as a kettle. Every unit comes with a private bathroom with slippers. Towels and bed linen are available.\n\nVietnam Museum of Ethnology is 4 km from ISTAY Hotel Apartment 5, while Giang Vo Exhibition Center is 5 km away. The nearest airport is Noi Bai International Airport, 23 km from the property.", "usefulInfo": [], "features": [{"Internet access": ["Free Wi-Fi in all rooms"]}, {"Services and conveniences": ["Smoking area"]}, {"Access": ["Pets allowed"]}, {"Available in all rooms": ["Air conditioning", "Bathtub", "Desk", "Fan", "Free bottled water", "Hair dryer", "Kitchenware", "Microwave", "Refrigerator", "Satellite/cable channels", "Shower", "TV", "TV [flat screen]"]}], "rooms": [{"id": 13087304, "name": "Deluxe Double Room", "facilities": {"Bathroom and toiletries": ["Hair dryer"], "Entertainment ": ["Satellite/cable channels"], "Comforts": ["Air conditioning", "Fan"], "Dining, drinking, and snacking": ["Kitchenware", "Microwave", "Refrigerator"], "Layout and furnishings": ["Desk"]}}, {"id": 13087117, "name": "One-Bedroom Apartment", "facilities": {"Bathroom and toiletries": ["Hair dryer"], "Entertainment ": ["Satellite/cable channels"], "Comforts": ["Air conditioning", "Fan"], "Dining, drinking, and snacking": ["Kitchenware", "Microwave", "Refrigerator"], "Layout and furnishings": ["Desk"]}}], "nearbyProperties": [{"categoryName": "Airports", "places": [{"distance": 11.88, "distanceDisplay": "12 km", "distanceUnit": "km", "name": "Gia Lam Airport (VGL)"}, {"distance": 23.14, "distanceDisplay": "23 km", "distanceUnit": "km", "name": "Noi Bai International Airport (HAN)"}]}, {"categoryName": "Public transportation", "places": [{"distance": 6.97, "distanceDisplay": "7 km", "distanceUnit": "km", "name": "Hanoi Railway Station"}, {"distance": 7.02, "distanceDisplay": "7 km", "distanceUnit": "km", "name": "Le Duan Railway Station"}]}, {"categoryName": "Hospital or clinic", "places": [{"distance": 2.03, "distanceDisplay": "2 km", "distanceUnit": "km", "name": "Benh Vien Y Hoc Co Truyen Bo Cong An"}]}, {"categoryName": "Pharmacy", "places": [{"distance": 0.91, "distanceDisplay": "900 m", "distanceUnit": "km", "name": "Hung Gia 2 Drugstore"}]}, {"categoryName": "Convenience store", "places": [{"distance": 0.58, "distanceDisplay": "550 m", "distanceUnit": "km", "name": "Vinmart"}]}, {"categoryName": "Cash withdrawal", "places": [{"distance": 0.66, "distanceDisplay": "650 m", "distanceUnit": "km", "name": "ATM"}]}]}