{"country": "Vietnam", "city": "Hanoi", "longitude": "105.878227667354", "latitude": "21.0476119115526", "name": "New Life Hotel", "stars": "2", "address": "No.20, 61 alley, Nguyen Son Street,, Long Bien District, Hanoi, Vietnam", "url": "https://www.agoda.com/new-life-hotel/hotel/hanoi-vn.html", "hotelId": 394074, "hotelDesc": "When visiting Hanoi, you'll feel right at home at New Life Hotel, which offers quality accommodation and great service. Only from the city center, the hotel's strategic location ensures that guests can quickly and easily reach many local points of interest. A haven of rest and relaxation, the hotel will offer total renewal just steps away from the city's numerous attractions such as Gia Lam, Gia Lam Airport, Savico Megamall.<BR><BR> Take advantage of a wealth of unrivaled services and amenities at this Hanoi hotel. For the comfort and convenience of guests, the hotel offers free Wi-Fi in all rooms, Wi-Fi in public areas, valet parking, airport transfer, tours.<BR><BR> All guest accommodations feature thoughtful amenities to ensure an unparalleled sense of comfort. Besides, the hotel's host of recreational offerings ensures you have plenty to do during your stay. New Life Hotel is an ideal place of stay for travelers seeking charm, comfort and convenience in Hanoi.", "usefulInfo": [{"Name": "Check-in/Check-out", "Items": [{"Title": "Check-in from", "Description": "10:00 AM"}, {"Title": "Check-out until", "Description": "12:00 PM"}]}, {"Name": "Getting around", "Items": [{"Title": "Airport transfer fee", "Description": "500000 VND"}, {"Title": "Travel time to airport (minutes)", "Description": "90"}]}, {"Name": "The property", "Items": [{"Title": "Number of rooms ", "Description": "15"}, {"Title": "Room voltage", "Description": "220"}, {"Title": "Year hotel opened", "Description": "2011"}]}], "features": [{"Internet access": ["Free Wi-Fi in all rooms", "Wi-Fi in public areas"]}, {"Getting around": ["Airport transfer", "Shuttle service", "Valet parking"]}, {"Things to do, ways to relax": ["Tours"]}, {"Services and conveniences": ["Concierge", "Laundry service", "Salon", "Smoking area"]}, {"Access": ["Pets allowed"]}, {"Available in all rooms": ["Air conditioning", "Free bottled water", "Internet access \u2013 wireless", "Mini bar", "Non-smoking room", "Satellite/cable channels", "Seating area", "Shower", "Telephone", "Toiletries", "Wake-up service", "Wi-Fi [free]"]}, {"Languages spoken": ["English", "Vietnamese"]}], "rooms": [{"id": 3999057, "name": "Double Room", "facilities": {"Bathroom and toiletries": ["Toiletries"], "Entertainment ": ["Free Wi-Fi in all rooms", "Satellite/cable channels", "Telephone"], "Comforts": ["Air conditioning", "Wake-up service"], "Dining, drinking, and snacking": ["Mini bar"], "Layout and furnishings": ["Seating area"]}}, {"id": 3999058, "name": "Twin Room", "facilities": {"Bathroom and toiletries": ["Toiletries"], "Entertainment ": ["Free Wi-Fi in all rooms", "Satellite/cable channels", "Telephone"], "Comforts": ["Air conditioning", "Fan", "Wake-up service"], "Dining, drinking, and snacking": ["Mini bar"], "Layout and furnishings": ["Desk", "Seating area"]}}], "nearbyProperties": [{"categoryName": "Airports", "places": [{"distance": 1.2, "distanceDisplay": "1.2 km", "distanceUnit": "km", "name": "Gia Lam Airport (VGL)"}, {"distance": 20.31, "distanceDisplay": "20 km", "distanceUnit": "km", "name": "Noi Bai International Airport (HAN)"}]}, {"categoryName": "Public transportation", "places": [{"distance": 4.34, "distanceDisplay": "4.3 km", "distanceUnit": "km", "name": "Le Duan Railway Station"}, {"distance": 4.57, "distanceDisplay": "4.6 km", "distanceUnit": "km", "name": "Hanoi Railway Station"}]}, {"categoryName": "Hospital or clinic", "places": [{"distance": 3.52, "distanceDisplay": "3.5 km", "distanceUnit": "km", "name": "Benh Vien Tam Than Ha Noi"}]}, {"categoryName": "Pharmacy", "places": [{"distance": 0.16, "distanceDisplay": "150 m", "distanceUnit": "km", "name": "Truc Tam 3 Drugstore"}]}, {"categoryName": "Convenience store", "places": [{"distance": 2.95, "distanceDisplay": "3 km", "distanceUnit": "km", "name": "Circle K"}]}, {"categoryName": "Cash withdrawal", "places": [{"distance": 0.59, "distanceDisplay": "550 m", "distanceUnit": "km", "name": "ATM"}]}]}