{"country": "Vietnam", "city": "Hanoi", "longitude": "105.778489593918", "latitude": "21.0440227478391", "name": "Pho Vang 5", "stars": "1", "address": "55 Pham Than Duat, Tu Liem District, Hanoi, Vietnam", "url": "https://www.agoda.com/pho-vang-5/hotel/hanoi-vn.html", "hotelId": 847725, "hotelDesc": "Set in Hanoi, 2.1 km from Vietnam Museum of Ethnology, Pho Vang 5 features air-conditioned rooms with free WiFi.\n\nRooms have a flat-screen TV with cable channels. Certain rooms feature a seating area where you can relax. Every room includes a private bathroom.\n\nThere is a 24-hour front desk at the property.\n\nPhu Tay Ho is 5 km from Pho Vang 5, while Giang Vo Exhibition Center is 5 km from the property. Noi Bai International Airport is 19 km away.", "usefulInfo": [], "features": [{"Internet access": ["Free Wi-Fi in all rooms"]}, {"Services and conveniences": ["Laundry service", "Smoking area"]}, {"Access": ["Front desk [24-hour]", "Pets allowed"]}, {"Available in all rooms": ["Air conditioning", "Free bottled water", "Mini bar", "Satellite/cable channels", "Seating area", "Shower", "Telephone", "TV [flat screen]"]}, {"Languages spoken": ["Vietnamese"]}], "rooms": [{"id": 4325839, "name": "Double or Twin Room", "facilities": {"Entertainment ": ["Free Wi-Fi in all rooms", "Satellite/cable channels", "Telephone"], "Comforts": ["Air conditioning"], "Dining, drinking, and snacking": ["Mini bar"], "Layout and furnishings": ["Seating area"]}}], "nearbyProperties": [{"categoryName": "Airports", "places": [{"distance": 11.26, "distanceDisplay": "11 kilometers to", "distanceUnit": "kilometers to", "name": "Gia Lam Airport (VGL)"}, {"distance": 19.45, "distanceDisplay": "19 kilometers to", "distanceUnit": "kilometers to", "name": "Noi Bai International Airport (HAN)"}]}, {"categoryName": "Public transportation", "places": [{"distance": 6.78, "distanceDisplay": "7 kilometers to", "distanceUnit": "kilometers to", "name": "Le Duan Railway Station"}, {"distance": 7.02, "distanceDisplay": "7 kilometers to", "distanceUnit": "kilometers to", "name": "Hanoi Railway Station"}]}, {"categoryName": "Hospital or clinic", "places": [{"distance": 1.08, "distanceDisplay": "1.1 kilometers to", "distanceUnit": "kilometers to", "name": "Benh Vien Da Khoa Y Hoc Co Truyen"}]}, {"categoryName": "Pharmacy", "places": [{"distance": 1.46, "distanceDisplay": "1.5 kilometers to", "distanceUnit": "kilometers to", "name": "Phan Kim Pharmacy"}]}, {"categoryName": "Convenience store", "places": [{"distance": 0.83, "distanceDisplay": "800 meters to", "distanceUnit": "kilometers to", "name": "Circle K"}]}, {"categoryName": "Cash withdrawal", "places": [{"distance": 0.99, "distanceDisplay": "950 meters to", "distanceUnit": "kilometers to", "name": "ATM"}]}]}