{"country": "Vietnam", "city": "Hanoi", "longitude": "105.79047", "latitude": "21.038017", "name": "Poonsa Serviced Apartment 1", "stars": "3", "address": "No. 6 Lane 89 Nguyen Phong Sac Street, Cau Giay District, Cau Giay District, Hanoi, Vietnam", "url": "https://www.agoda.com/poonsa-serviced-apartment-1/hotel/hanoi-vn.html", "hotelId": 1846710, "hotelDesc": "Featuring air conditioning, Poonsa Serviced Apartment 1 is located in Ph\u01b0\u01a1ng Vi\u00ean, 7 km from Hanoi. Y\u00ean B\u00e0i is 37 km from the property. Private parking is available on site.\n\nAll units have a TV. Some units include a terrace and/or balcony with city views. There is also a kitchen, fitted with an oven. Every unit is fitted with a private bathroom with a bath or shower and bathrobes. The apartment features free WiFi.\n\nPoonsa Serviced Apartment 1 also includes a terrace.\n\nThe nearest airport is Noi Bai International Airport, 20 km from Poonsa Serviced Apartment 1.", "usefulInfo": [], "features": [{"Internet access": ["Free Wi-Fi in all rooms"]}, {"Services and conveniences": ["Smoking area"]}, {"Access": ["Pets allowed"]}, {"Available in all rooms": ["Air conditioning", "Balcony/terrace", "Bathrobes", "Clothes dryer", "Desk", "Free bottled water", "Hair dryer", "In-room safe box", "Ironing facilities", "Microwave", "Mini bar", "Refrigerator", "Satellite/cable channels", "Shower", "Soundproofing", "Telephone", "TV"]}], "rooms": [{"id": 12373827, "name": "Two-Bedroom Apartment", "facilities": {"Bathroom and toiletries": ["Bathrobes", "Hair dryer", "Mirror", "Towels"], "Entertainment ": ["Satellite/cable channels", "Telephone"], "Comforts": ["Air conditioning", "Soundproofing"], "Dining, drinking, and snacking": ["Microwave", "Mini bar", "Refrigerator"], "Layout and furnishings": ["Desk"], "Clothing and laundry": ["Closet", "Clothes dryer", "Ironing facilities"], "Safety and security features": ["In-room safe box"]}}, {"id": 12373988, "name": "Studio Apartment", "facilities": {"Bathroom and toiletries": ["Bathrobes", "Hair dryer", "Mirror", "Toiletries", "Towels"], "Entertainment ": ["Satellite/cable channels", "Telephone"], "Comforts": ["Air conditioning", "Alarm clock", "Fan", "Mosquito net", "Soundproofing"], "Dining, drinking, and snacking": ["Kitchenette", "Microwave", "Mini bar", "Refrigerator"], "Layout and furnishings": ["Desk", "Seating area"], "Clothing and laundry": ["Closet", "Clothes dryer", "Ironing facilities"], "Safety and security features": ["In-room safe box"]}}, {"id": 12373536, "name": "One-Bedroom Apartment", "facilities": {"Bathroom and toiletries": ["Bathrobes", "Hair dryer", "Mirror", "Towels"], "Entertainment ": ["Satellite/cable channels", "Telephone"], "Comforts": ["Air conditioning", "Soundproofing"], "Dining, drinking, and snacking": ["Microwave", "Mini bar", "Refrigerator"], "Layout and furnishings": ["Desk"], "Clothing and laundry": ["Closet", "Clothes dryer", "Ironing facilities"], "Safety and security features": ["In-room safe box"]}}], "nearbyProperties": [{"categoryName": "Airports", "places": [{"distance": 10.01, "distanceDisplay": "10 kilometers to", "distanceUnit": "kilometers to", "name": "Gia Lam Airport (VGL)"}, {"distance": 19.97, "distanceDisplay": "20 kilometers to", "distanceUnit": "kilometers to", "name": "Noi Bai International Airport (HAN)"}]}, {"categoryName": "Public transportation", "places": [{"distance": 5.42, "distanceDisplay": "5 kilometers to", "distanceUnit": "kilometers to", "name": "Le Duan Railway Station"}, {"distance": 5.63, "distanceDisplay": "6 kilometers to", "distanceUnit": "kilometers to", "name": "Hanoi Railway Station"}]}, {"categoryName": "Hospital or clinic", "places": [{"distance": 1.24, "distanceDisplay": "1.2 kilometers to", "distanceUnit": "kilometers to", "name": "Benh Vien Da Khoa Y Hoc Co Truyen"}]}, {"categoryName": "Pharmacy", "places": [{"distance": 0.27, "distanceDisplay": "250 meters to", "distanceUnit": "kilometers to", "name": "Tam An Drugstore"}]}, {"categoryName": "Convenience store", "places": [{"distance": 0.43, "distanceDisplay": "400 meters to", "distanceUnit": "kilometers to", "name": "Vinmart"}]}, {"categoryName": "Cash withdrawal", "places": [{"distance": 0.72, "distanceDisplay": "700 meters to", "distanceUnit": "kilometers to", "name": "ATM"}]}]}