{"country": "Vietnam", "city": "Hanoi", "longitude": "105.834277421236", "latitude": "21.0259994407442", "name": "Sao Mai hotel", "stars": "3", "address": "23 Thong Phong Alley, Ton Duc Thang Street, Dong Da District, Hanoi, Vietnam, 100000", "url": "https://www.agoda.com/sao-mai-hotel/hotel/hanoi-vn.html", "hotelId": 2061982, "hotelDesc": "Well-placed in the business, culture area of Hanoi city, Sao Mai hotel provides a most conducive spot for you to take a break from your busy days. The hotel lies from the city center and provides accessibility to important town facilities. With its convenient location, the hotel offers easy access to the city's must-see destinations.<BR><BR> The facilities and services provided by Sao Mai hotel ensure a pleasant stay for guests. While lodging at this wonderful property, guests can enjoy free Wi-Fi in all rooms, 24-hour security, luggage storage, Wi-Fi in public areas, room service.<BR><BR> Step into one of 62 inviting rooms and escape the stresses of the day with a wide range of amenities such as television LCD/plasma screen, mirror, slippers, sofa, towels which can be found in some rooms. Besides, the hotel's host of recreational offerings ensures you have plenty to do during your stay. Sao Mai hotel is a smart choice for travelers to Hanoi, offering a relaxed and hassle-free stay every time.", "usefulInfo": [{"Name": "Check-in/Check-out", "Items": [{"Title": "Check-in from", "Description": "02:00 PM"}, {"Title": "Check-out from", "Description": "12:00 PM"}]}, {"Name": "The property", "Items": [{"Title": "Number of rooms ", "Description": "62"}, {"Title": "Room voltage", "Description": "220"}, {"Title": "Year hotel opened", "Description": "2016"}]}], "features": [{"Internet access": ["Free Wi-Fi in all rooms", "Wi-Fi in public areas"]}, {"Getting around": ["Airport transfer"]}, {"Things to do, ways to relax": ["Tours"]}, {"Dining, drinking, and snacking": ["Breakfast [free]", "Restaurants", "Room service"]}, {"Services and conveniences": ["Laundry service", "Luggage storage", "Smoking area"]}, {"Access": ["Elevator", "Pets allowed", "Security [24-hour]"]}, {"Available in all rooms": ["Air conditioning", "Free bottled water", "Internet access \u2013 wireless", "Wi-Fi [free]"]}, {"Languages spoken": ["English", "Vietnamese"]}], "rooms": [{"id": 12032847, "name": "Suite", "facilities": {"Bathroom and toiletries": ["Hair dryer", "Mirror", "Toiletries", "Towels"], "Entertainment ": ["Free Wi-Fi in all rooms", "Satellite/cable channels", "Telephone"], "Comforts": ["Air conditioning", "Blackout curtains", "Slippers", "Wake-up service"], "Dining, drinking, and snacking": ["Free bottled water", "Mini bar"], "Layout and furnishings": ["Desk", "Seating area", "Separate living room", "Sofa"]}}, {"id": 12029824, "name": "Deluxe Double or Twin", "facilities": {"Entertainment ": ["Free Wi-Fi in all rooms"], "Comforts": ["Air conditioning", "Blackout curtains"], "Dining, drinking, and snacking": ["Free bottled water"]}}, {"id": 12029817, "name": "Superior Double or Twin", "facilities": {"Entertainment ": ["Free Wi-Fi in all rooms"], "Comforts": ["Air conditioning", "Blackout curtains"], "Dining, drinking, and snacking": ["Free bottled water"]}}, {"id": 12029801, "name": "Standard Double or Twin", "facilities": {"Entertainment ": ["Free Wi-Fi in all rooms"], "Comforts": ["Air conditioning"], "Dining, drinking, and snacking": ["Free bottled water"]}}], "nearbyProperties": [{"categoryName": "Airports", "places": [{"distance": 5.67, "distanceDisplay": "6 km", "distanceUnit": "km", "name": "Gia Lam Airport (VGL)"}, {"distance": 21.45, "distanceDisplay": "21 km", "distanceUnit": "km", "name": "Noi Bai International Airport (HAN)"}]}, {"categoryName": "Public transportation", "places": [{"distance": 0.82, "distanceDisplay": "800 m", "distanceUnit": "km", "name": "Le Duan Railway Station"}, {"distance": 0.89, "distanceDisplay": "850 m", "distanceUnit": "km", "name": "Hanoi Railway Station"}]}, {"categoryName": "Hospital or clinic", "places": [{"distance": 0.5, "distanceDisplay": "450 m", "distanceUnit": "km", "name": "Benh Vien Da Lieu Ha Noi"}]}, {"categoryName": "Pharmacy", "places": [{"distance": 0.08, "distanceDisplay": "80 m", "distanceUnit": "km", "name": "Trang An Drugstore"}]}, {"categoryName": "Convenience store", "places": [{"distance": 0.84, "distanceDisplay": "800 m", "distanceUnit": "km", "name": "Vinmart"}]}, {"categoryName": "Cash withdrawal", "places": [{"distance": 0.74, "distanceDisplay": "700 m", "distanceUnit": "km", "name": "ATM"}]}]}