{"country": "Vietnam", "city": "Hanoi", "longitude": "105.805807113647", "latitude": "21.0099428521637", "name": "Sunny Hotel 2", "stars": "3", "address": "Lane 170 Hoang Ngan Str., Trung Hoa, Cau Giay Dist. (Lane 11 Nguyen Thi Dinh Str.), Trung Hoa Nhan Chinh, Hanoi, Vietnam", "url": "https://www.agoda.com/sunny-hotel-2/hotel/hanoi-vn.html", "hotelId": 247385, "hotelDesc": "Well-positioned in Trung Hoa Nhan Chinh, Sunny Hotel 2 is the ideal point of departure for your excursions in Hanoi. The excitement of the city center is only away. This modern hotel is in the vicinity of popular city attractions such as Benh Vien Mat Sai Gon - Ha Noi, Tran Duy Hung Street, Trung Tam Y Te Du Phong Ha Noi.<BR><BR> Sunny Hotel 2 offers impeccable service and all the essential amenities to invigorate travelers. This hotel offers numerous on-site facilities to satisfy even the most discerning guest.<BR><BR> The hotel features 20 beautifully appointed guest rooms, many of which include internet access \u2013 wireless, internet access \u2013 wireless (complimentary), air conditioning, desk, mini bar. Besides, the hotel's host of recreational offerings ensures you have plenty to do during your stay. With an ideal location and facilities to match, Sunny Hotel 2 hits the spot in many ways.", "usefulInfo": [{"Name": "The property", "Items": [{"Title": "Number of rooms ", "Description": "20"}]}], "features": [{"Internet access": ["Free Wi-Fi in all rooms", "Wi-Fi in public areas"]}, {"Getting around": ["Airport transfer"]}, {"Dining, drinking, and snacking": ["Coffee shop", "Restaurants", "Room service"]}, {"Services and conveniences": ["Laundry service", "Safety deposit boxes", "Smoking area"]}, {"Access": ["Elevator", "Pets allowed"]}, {"Available in all rooms": ["Air conditioning", "Coffee/tea maker", "Daily newspaper", "Free bottled water", "Internet access \u2013 LAN", "Internet access \u2013 wireless", "Mini bar", "Refrigerator", "Satellite/cable channels", "Shower", "TV", "Wi-Fi [free]"]}, {"Languages spoken": ["English", "Vietnamese"]}], "rooms": [{"id": 3982959, "name": "Deluxe", "facilities": {"Bathroom and toiletries": ["Hair dryer"], "Entertainment ": ["Free Wi-Fi in all rooms", "Satellite/cable channels", "Telephone"], "Comforts": ["Air conditioning", "Daily newspaper"], "Dining, drinking, and snacking": ["Coffee/tea maker", "Free bottled water", "Mini bar", "Refrigerator"], "Layout and furnishings": ["Desk"]}}, {"id": 3982961, "name": "Suite", "facilities": {"Bathroom and toiletries": ["Hair dryer"], "Entertainment ": ["Free Wi-Fi in all rooms", "Satellite/cable channels", "Telephone"], "Comforts": ["Air conditioning", "Daily newspaper"], "Dining, drinking, and snacking": ["Coffee/tea maker", "Free bottled water", "Mini bar", "Refrigerator"], "Layout and furnishings": ["Desk"], "Safety and security features": ["In-room safe box"]}}, {"id": 3982960, "name": "Executive", "facilities": {"Bathroom and toiletries": ["Hair dryer"], "Entertainment ": ["Free Wi-Fi in all rooms", "Satellite/cable channels", "Telephone"], "Comforts": ["Air conditioning", "Daily newspaper"], "Dining, drinking, and snacking": ["Coffee/tea maker", "Free bottled water", "Mini bar", "Refrigerator"], "Layout and furnishings": ["Desk"]}}], "nearbyProperties": [{"categoryName": "Airports", "places": [{"distance": 9.06, "distanceDisplay": "9 km", "distanceUnit": "km", "name": "Gia Lam Airport (VGL)"}, {"distance": 23.02, "distanceDisplay": "23 km", "distanceUnit": "km", "name": "Noi Bai International Airport (HAN)"}]}, {"categoryName": "Public transportation", "places": [{"distance": 4.1, "distanceDisplay": "4.1 km", "distanceUnit": "km", "name": "Hanoi Railway Station"}, {"distance": 4.26, "distanceDisplay": "4.3 km", "distanceUnit": "km", "name": "Le Duan Railway Station"}]}, {"categoryName": "Hospital or clinic", "places": [{"distance": 0.51, "distanceDisplay": "500 m", "distanceUnit": "km", "name": "Benh Vien Mat Sai Gon - Ha Noi"}]}, {"categoryName": "Pharmacy", "places": [{"distance": 0.43, "distanceDisplay": "400 m", "distanceUnit": "km", "name": "Nam An Duoc Drugstore"}]}, {"categoryName": "Convenience store", "places": [{"distance": 0.16, "distanceDisplay": "150 m", "distanceUnit": "km", "name": "Vinmart"}]}, {"categoryName": "Cash withdrawal", "places": [{"distance": 2.44, "distanceDisplay": "2.4 km", "distanceUnit": "km", "name": "ATM"}]}]}