{"country": "Vietnam", "city": "Hanoi", "longitude": "105.83861", "latitude": "21.052065", "name": "Thanh Nga Guest House", "stars": "1", "address": "55 Nghi Tam, Tay Ho, Tay Ho District, Hanoi, Vietnam", "url": "https://www.agoda.com/thanh-nga-guest-house/hotel/hanoi-vn.html", "hotelId": 847794, "hotelDesc": "Thanh Nga Guest House is located in Hanoi, 500 metres from Tran Quoc Pagoda and 600 metres from West Lake.\n\nAll rooms are equipped with a TV. Certain units feature a seating area for your convenience. The rooms include a private bathroom. Thanh Nga Guest House features free WiFi throughout the property.\n\nThere is ticket service at the property.\n\nQuan Thanh Temple is 1 km from Thanh Nga Guest House, while Ho Chi Minh Mausoleum is 1.8 km away. Noi Bai International Airport is 18 km from the property.", "usefulInfo": [], "features": [{"Internet access": ["Free Wi-Fi in all rooms"]}, {"Services and conveniences": ["Smoking area"]}, {"Access": ["Pets allowed"]}, {"Available in all rooms": ["Air conditioning", "Fan", "Free bottled water", "Heating", "Mini bar", "Seating area", "Shower", "TV"]}], "rooms": [{"id": 4323960, "name": "Double Room", "facilities": {"Entertainment ": ["TV"], "Comforts": ["Air conditioning", "Fan", "Heating"], "Dining, drinking, and snacking": ["Mini bar"], "Layout and furnishings": ["Seating area"]}}, {"id": 12446212, "name": "Family Room", "facilities": {"Entertainment ": ["TV"], "Comforts": ["Air conditioning", "Fan", "Heating"], "Dining, drinking, and snacking": ["Mini bar"], "Layout and furnishings": ["Seating area"]}}, {"id": 12446206, "name": "Double Room", "facilities": {"Entertainment ": ["TV"], "Comforts": ["Air conditioning", "Fan", "Heating"], "Dining, drinking, and snacking": ["Mini bar"], "Layout and furnishings": ["Seating area"]}}, {"id": 4319922, "name": "Family Room", "facilities": {"Entertainment ": ["TV"], "Comforts": ["Air conditioning", "Fan", "Heating"], "Dining, drinking, and snacking": ["Mini bar"], "Layout and furnishings": ["Seating area"]}}], "nearbyProperties": [{"categoryName": "Airports", "places": [{"distance": 5.17, "distanceDisplay": "5 km", "distanceUnit": "km", "name": "Gia Lam Airport (VGL)"}, {"distance": 18.68, "distanceDisplay": "19 km", "distanceUnit": "km", "name": "Noi Bai International Airport (HAN)"}]}, {"categoryName": "Public transportation", "places": [{"distance": 2.62, "distanceDisplay": "2.6 km", "distanceUnit": "km", "name": "Le Duan Railway Station"}, {"distance": 3.17, "distanceDisplay": "3.2 km", "distanceUnit": "km", "name": "Hanoi Railway Station"}]}, {"categoryName": "Hospital or clinic", "places": [{"distance": 2.34, "distanceDisplay": "2.3 km", "distanceUnit": "km", "name": "Saint Paul General Hospital"}]}, {"categoryName": "Pharmacy", "places": [{"distance": 1.03, "distanceDisplay": "1 km", "distanceUnit": "km", "name": "Bao Ngoc Drugstore"}]}, {"categoryName": "Convenience store", "places": [{"distance": 1.1, "distanceDisplay": "1.1 km", "distanceUnit": "km", "name": "Circle K"}]}, {"categoryName": "Cash withdrawal", "places": [{"distance": 1.71, "distanceDisplay": "1.7 km", "distanceUnit": "km", "name": "ATM"}]}]}