{"country": "Vietnam", "city": "Hanoi", "longitude": "105.852345585954", "latitude": "21.0368465700427", "name": "The Time House Hanoi", "stars": "3", "address": "18 Dao Duy Tu Street, Hoan Kiem District, Old Quarter, Hanoi, Vietnam", "url": "https://www.agoda.com/the-time-house-hanoi/hotel/hanoi-vn.html", "hotelId": 271590, "hotelDesc": "Designed for both business and leisure travel, The Time House Hanoi is ideally situated in Old Quarter; one of the city's most popular locales. The city center is merely 10 Miles away and the airport can be reached within 35 minutes. This modern hotel is in the vicinity of popular city attractions such as Kuy Son Propaganda Art, Den Quan De, Hanoi Old Quarter Culture Exchange Center.<BR><BR> At The Time House Hanoi, every effort is made to make guests feel comfortable. To do so, the hotel provides the best in services and amenities. Top features of the hotel include 24-hour room service, free Wi-Fi in all rooms, daily housekeeping, private check in/check out, 24-hour front desk.<BR><BR> All guest accommodations feature thoughtful amenities to ensure an unparalleled sense of comfort. Besides, the hotel's host of recreational offerings ensures you have plenty to do during your stay. The Time House Hanoi is a smart choice for travelers to Hanoi, offering a relaxed and hassle-free stay every time.", "usefulInfo": [{"Name": "Check-in/Check-out", "Items": [{"Title": "Check-in from", "Description": "10:00 AM"}, {"Title": "Check-out until", "Description": "12:00 AM"}, {"Title": "Reception open until", "Description": "11:30 PM"}]}, {"Name": "Getting around", "Items": [{"Title": "Distance from city center", "Description": "10 Miles"}, {"Title": "Travel time to airport (minutes)", "Description": "35"}]}, {"Name": "The property", "Items": [{"Title": "Number of floors", "Description": "6"}, {"Title": "Number of restaurants", "Description": "1"}, {"Title": "Number of rooms ", "Description": "20"}, {"Title": "Year hotel opened", "Description": "2014"}, {"Title": "Most recent hotel renovation", "Description": "2015"}]}], "features": [{"Internet access": ["Free Wi-Fi in all rooms", "Wi-Fi in public areas"]}, {"Getting around": ["Airport transfer", "Bicycle rental", "Rental car ", "Valet parking"]}, {"Things to do, ways to relax": ["Tours"]}, {"Dining, drinking, and snacking": ["Bar", "Coffee shop", "Restaurants", "Room service", "Room service [24-hour]", "Shared kitchen"]}, {"Services and conveniences": ["Cash withdrawal", "Concierge", "Currency exchange", "Daily housekeeping", "Doorman ", "Laundry service", "Library", "Luggage storage", "Safety deposit boxes", "Salon", "Smoking area"]}, {"For the kids": ["Babysitting service", "Family room"]}, {"Access": ["Check-in/out [private]", "Check-in [24-hour]", "Elevator", "Front desk [24-hour]", "Pets allowed"]}, {"Available in all rooms": ["Air conditioning", "Coffee/tea maker", "Desk", "Executive lounge access", "Fan", "Free bottled water", "Hair dryer", "Internet access \u2013 LAN", "Internet access \u2013 wireless", "Ironing facilities", "Kitchenette", "LAN Internet in room [free]", "Mini bar", "Non-smoking room", "Refrigerator", "Satellite/cable channels", "Seating area", "Shower", "Telephone", "TV", "TV [flat screen]", "Wi-Fi [free]"]}, {"Languages spoken": ["English", "Indonesian", "Malay", "Thai", "Vietnamese"]}], "rooms": [{"id": 3372174, "name": "Superior", "facilities": {"Bathroom and toiletries": ["Hair dryer"], "Entertainment ": ["Free Wi-Fi in all rooms", "Satellite/cable channels", "Telephone", "Video game console"], "Comforts": ["Air conditioning", "Daily newspaper", "Executive lounge access", "Fan", "Wake-up service"], "Dining, drinking, and snacking": ["Coffee/tea maker", "Kitchenette", "Microwave", "Mini bar", "Refrigerator"], "Layout and furnishings": ["Desk", "Seating area"], "Clothing and laundry": ["Closet", "Ironing facilities"], "Safety and security features": ["In-room safe box", "Laptop safe box"]}}, {"id": 3372178, "name": "Family Suite", "facilities": {"Bathroom and toiletries": ["Hair dryer"], "Entertainment ": ["Free Wi-Fi in all rooms", "Satellite/cable channels", "Telephone"], "Comforts": ["Air conditioning", "Blackout curtains", "Executive lounge access", "Fan", "Wake-up service"], "Dining, drinking, and snacking": ["Coffee/tea maker", "Kitchenette", "Mini bar", "Refrigerator"], "Layout and furnishings": ["Desk", "Seating area"], "Clothing and laundry": ["Closet", "Ironing facilities"], "Safety and security features": ["In-room safe box"]}}, {"id": 3372175, "name": "Deluxe", "facilities": {"Bathroom and toiletries": ["Hair dryer"], "Entertainment ": ["Free Wi-Fi in all rooms", "Satellite/cable channels", "Telephone"], "Comforts": ["Air conditioning", "Blackout curtains", "Executive lounge access", "Fan", "Wake-up service"], "Dining, drinking, and snacking": ["Coffee/tea maker", "Kitchenette", "Microwave", "Mini bar", "Refrigerator"], "Layout and furnishings": ["Desk", "Seating area"], "Clothing and laundry": ["Closet", "Ironing facilities", "Washing machine"], "Safety and security features": ["In-room safe box"]}}], "nearbyProperties": [{"categoryName": "Airports", "places": [{"distance": 3.59, "distanceDisplay": "3.6 kilometers to", "distanceUnit": "kilometers to", "name": "Gia Lam Airport (VGL)"}, {"distance": 20.63, "distanceDisplay": "21 kilometers to", "distanceUnit": "kilometers to", "name": "Noi Bai International Airport (HAN)"}]}, {"categoryName": "Public transportation", "places": [{"distance": 1.44, "distanceDisplay": "1.4 kilometers to", "distanceUnit": "kilometers to", "name": "Le Duan Railway Station"}, {"distance": 1.79, "distanceDisplay": "1.8 kilometers to", "distanceUnit": "kilometers to", "name": "Hanoi Railway Station"}]}, {"categoryName": "Hospital or clinic", "places": [{"distance": 1.25, "distanceDisplay": "1.2 kilometers to", "distanceUnit": "kilometers to", "name": "Benh Vien Phu San Ha Noi"}]}, {"categoryName": "Pharmacy", "places": [{"distance": 0.08, "distanceDisplay": "80 meters to", "distanceUnit": "kilometers to", "name": "Nguyen Thi Lan Anh Pharmacy"}]}, {"categoryName": "Convenience store", "places": [{"distance": 0.15, "distanceDisplay": "150 meters to", "distanceUnit": "kilometers to", "name": "Circle K"}]}, {"categoryName": "Cash withdrawal", "places": [{"distance": 0, "distanceDisplay": "ATM on site", "distanceUnit": "", "name": ""}]}]}