{"country": "Vietnam", "city": "Hanoi", "longitude": "105.823715", "latitude": "21.060308", "name": "Zo Apartment Hanoi", "stars": "", "address": "14 Velly 12, Dang Thai Mai, Tay Ho District, Hanoi, Vietnam", "url": "https://www.agoda.com/zo-apartment-hanoi/hotel/hanoi-vn.html", "hotelId": 1681106, "hotelDesc": "Featuring free WiFi and a barbecue, Zo Apartment Hanoi offers pet-friendly accommodation in Hanoi, 600 metres from Phu Tay Ho. Guests can enjoy the on-site bar.\n\nRooms have a flat-screen TV with cable channels. Certain rooms include a seating area for your convenience. You will find a kettle in the room. Each room comes with a private bathroom fitted with a bidet.\n\nYou will find dry cleaning services at the property.\n\nYou can play darts at this guest house, and bike hire is available. The guest house also offers car hire. West Lake is 1.6 km from Zo Apartment Hanoi, while Tran Quoc Pagoda is 1.9 km away. The nearest airport is Noi Bai International Airport, 17 km from Zo Apartment Hanoi.", "usefulInfo": [], "features": [{"Internet access": ["Free Wi-Fi in all rooms"]}, {"Services and conveniences": ["Smoking area"]}, {"Access": ["Pets allowed"]}, {"Available in all rooms": ["Air conditioning", "Balcony/terrace", "Desk", "Free bottled water", "Kitchenette", "Satellite/cable channels", "Seating area", "TV", "TV [flat screen]"]}], "rooms": [{"id": 10711607, "name": "Deluxe Apartment", "facilities": {"Entertainment ": ["Satellite/cable channels"], "Comforts": ["Air conditioning"], "Dining, drinking, and snacking": ["Kitchenette"], "Layout and furnishings": ["Desk", "Seating area"]}}, {"id": 10719640, "name": "Studio Apartment", "facilities": {"Entertainment ": ["Satellite/cable channels"], "Comforts": ["Air conditioning"], "Dining, drinking, and snacking": ["Kitchenette"], "Layout and furnishings": ["Desk", "Seating area"]}}, {"id": 10712465, "name": "Standard Apartment", "facilities": {"Entertainment ": ["Satellite/cable channels"], "Comforts": ["Air conditioning"], "Dining, drinking, and snacking": ["Kitchenette", "Microwave", "Refrigerator"], "Layout and furnishings": ["Desk", "Seating area"]}}], "nearbyProperties": [{"categoryName": "Airports", "places": [{"distance": 6.91, "distanceDisplay": "7 km", "distanceUnit": "km", "name": "Gia Lam Airport (VGL)"}, {"distance": 17.55, "distanceDisplay": "18 km", "distanceUnit": "km", "name": "Noi Bai International Airport (HAN)"}]}, {"categoryName": "Public transportation", "places": [{"distance": 3.97, "distanceDisplay": "4 km", "distanceUnit": "km", "name": "Le Duan Railway Station"}, {"distance": 4.5, "distanceDisplay": "4.5 km", "distanceUnit": "km", "name": "Hanoi Railway Station"}]}, {"categoryName": "Hospital or clinic", "places": [{"distance": 2.21, "distanceDisplay": "2.2 km", "distanceUnit": "km", "name": "Benh Vien Lao Va Cac Benh Phoi Trung Uong"}]}, {"categoryName": "Pharmacy", "places": [{"distance": 0.68, "distanceDisplay": "650 m", "distanceUnit": "km", "name": "Tay Nguyen Thi Kim Thanh Drugstore"}]}, {"categoryName": "Convenience store", "places": [{"distance": 2.71, "distanceDisplay": "2.7 km", "distanceUnit": "km", "name": "Vinmart"}]}, {"categoryName": "Cash withdrawal", "places": [{"distance": 1.22, "distanceDisplay": "1.2 km", "distanceUnit": "km", "name": "ATM"}]}]}